stringly/__init__.py
stringly/error.py
stringly/proto.py
stringly/py.typed
stringly/serializer.py
stringly/util.py
stringly-1.0b2.dist-info/LICENSE
stringly-1.0b2.dist-info/METADATA
stringly-1.0b2.dist-info/WHEEL
stringly-1.0b2.dist-info/top_level.txt
stringly-1.0b2.dist-info/RECORD
