Metadata-Version: 2.1
Name: stringly
Version: 1.0b2
Summary: Stringly typed command line interface
Home-page: https://github.com/evalf/stringly
Author: Evalf
Author-email: info@evalf.com
License: MIT
Platform: UNKNOWN
Requires-Python: >=3.5
Requires-Dist: typing-extensions
